{
  "repos": {
    "stegcge": {
      "org": "StegGhost",
      "repo_slug": "StegCGE",
      "clone_url": "https://github.com/StegGhost/StegCGE.git",
      "default_branch": "main",
      "allowed_prefixes": [
        "cge/",
        "tests/",
        "docs/",
        "demo/",
        ".github/",
        "README.md",
        "requirements.txt",
        "run_demo.py",
        "LICENSE"
      ]
    },
    "automated_buildout": {
      "org": "StegGhost",
      "repo_slug": "automated_buildout",
      "clone_url": "https://github.com/StegGhost/automated_buildout.git",
      "default_branch": "main",
      "allowed_prefixes": [
        "buildout/",
        "engine/",
        "bundles/",
        "configs/",
        "docs/",
        "tests/",
        ".github/",
        "README.md",
        "requirements.txt",
        "LICENSE"
      ]
    },
    "entity_sandbox_runner": {
      "org": "StegGhost",
      "repo_slug": "entity-sandbox-runner",
      "clone_url": "https://github.com/StegGhost/entity-sandbox-runner.git",
      "default_branch": "main",
      "allowed_prefixes": [
        "runner/",
        "sandbox/",
        "experiments/",
        "configs/",
        "reports/",
        "docs/",
        "tests/",
        ".github/",
        "README.md",
        "requirements.txt",
        "LICENSE"
      ]
    },
    "stegverse_sandbox": {
      "org": "StegGhost",
      "repo_slug": "stegverse-sandbox",
      "clone_url": "https://github.com/StegGhost/stegverse-sandbox.git",
      "default_branch": "main",
      "allowed_prefixes": [
        "sandbox/",
        "engine/",
        "configs/",
        "docs/",
        "tests/",
        ".github/",
        "README.md",
        "requirements.txt",
        "LICENSE"
      ]
    },
    "ghost_pat_lab": {
      "org": "StegGhost",
      "repo_slug": "ghost-pat-lab",
      "clone_url": "https://github.com/StegGhost/ghost-pat-lab.git",
      "default_branch": "main",
      "allowed_prefixes": [
        "lab/",
        "experiments/",
        "tests/",
        "docs/",
        ".github/",
        "README.md",
        "requirements.txt",
        "LICENSE"
      ]
    },
    "stegverse_gsl": {
      "org": "StegVerse-org",
      "repo_slug": "stegverse-gsl",
      "clone_url": "https://github.com/StegVerse-org/stegverse-gsl.git",
      "default_branch": "main",
      "allowed_prefixes": [
        "sdk_assistant/",
        "schemas/",
        "engine/",
        "buildout/",
        "sandbox/",
        "receipts/",
        "tests/",
        "config/",
        "examples/",
        "docs/",
        ".github/",
        "buildout.yaml",
        "README.md",
        "requirements.txt",
        "LICENSE",
        "ARTIFACT_EVALUATION.md",
        "REPRODUCIBILITY.md"
      ]
    },
    "trust_kernel": {
      "org": "StegVerse-org",
      "repo_slug": "trust-kernel",
      "clone_url": "https://github.com/StegVerse-org/trust-kernel.git",
      "default_branch": "main",
      "allowed_prefixes": [
        "trust_kernel/",
        "api/",
        "kernel/",
        "receipts/",
        "schemas/",
        "tests/",
        "examples/",
        "docs/",
        "config/",
        ".github/",
        "README.md",
        "requirements.txt",
        "LICENSE",
        "ARTIFACT_EVALUATION.md",
        "REPRODUCIBILITY.md"
      ]
    },
    "stegverse_sdk": {
      "org": "StegVerse-org",
      "repo_slug": "StegVerse-SDK",
      "clone_url": "https://github.com/StegVerse-org/StegVerse-SDK.git",
      "default_branch": "main",
      "allowed_prefixes": [
        "sdk/",
        "stegverse_sdk/",
        "client/",
        "examples/",
        "tests/",
        "docs/",
        "config/",
        ".github/",
        "README.md",
        "requirements.txt",
        "LICENSE",
        "ARTIFACT_EVALUATION.md",
        "REPRODUCIBILITY.md"
      ]
    }
  },
  "repo_aliases": {
    "stegcge": "stegcge",
    "StegCGE": "stegcge",
    "automated_buildout": "automated_buildout",
    "automated-buildout": "automated_buildout",
    "entity_sandbox_runner": "entity_sandbox_runner",
    "entity-sandbox-runner": "entity_sandbox_runner",
    "stegverse_sandbox": "stegverse_sandbox",
    "stegverse-sandbox": "stegverse_sandbox",
    "ghost_pat_lab": "ghost_pat_lab",
    "ghost-pat-lab": "ghost_pat_lab",
    "stegverse_gsl": "stegverse_gsl",
    "stegverse-gsl": "stegverse_gsl",
    "trust_kernel": "trust_kernel",
    "trust-kernel": "trust_kernel",
    "stegverse_sdk": "stegverse_sdk",
    "StegVerse-SDK": "stegverse_sdk",
    "stegverse-sdk": "stegverse_sdk"
  },
  "target_sets": {
    "all": [
      "stegcge",
      "automated_buildout",
      "entity_sandbox_runner",
      "stegverse_sandbox",
      "ghost_pat_lab",
      "stegverse_gsl",
      "trust_kernel",
      "stegverse_sdk"
    ],
    "stegghost_all": [
      "stegcge",
      "automated_buildout",
      "entity_sandbox_runner",
      "stegverse_sandbox",
      "ghost_pat_lab"
    ],
    "stegverse_all": [
      "stegverse_gsl",
      "trust_kernel",
      "stegverse_sdk"
    ],
    "core_build": [
      "stegcge",
      "automated_buildout"
    ],
    "sandbox_stack": [
      "entity_sandbox_runner",
      "stegverse_sandbox"
    ],
    "gsl_stack": [
      "stegverse_gsl"
    ],
    "trust_stack": [
      "trust_kernel",
      "stegverse_sdk"
    ],
    "production_surface": [
      "trust_kernel",
      "stegverse_sdk"
    ]
  }
}
