{
  "blocked_count": 0,
  "checks_failed": [],
  "checks_passed": [
    "queue_json_exists",
    "latest_queue_item_exists",
    "queue_markdown_exists",
    "queue_execution_authority_false",
    "queue_install_authority_false",
    "item_count_matches",
    "latest_queue_item_matches_queue",
    "all_items_are_non_executing_review_records",
    "item_source_hashes_match",
    "queued_for_review_count_matches",
    "observe_only_count_matches",
    "blocked_count_matches"
  ],
  "execution_authority": false,
  "generated_at_utc": "2026-06-14T21:19:40.163559Z",
  "install_authority": false,
  "item_count": 1,
  "observe_only_count": 0,
  "queue_dir": "cge_intake",
  "queued_for_review_count": 1,
  "sandbox_receipt_queue_verification_version": "1.0",
  "status": "PASS"
}